<?xml version="1.0" encoding="UTF-8"?>

<Medication xmlns="http://hl7.org/fhir">
  <text>
    <status value="generated"/>
    <div xmlns="http://www.w3.org/1999/xhtml">
      <p>
        <b>Generated Narrative</b>
      </p>
      <p>
        <b>name</b>: Metoprolol
      </p>
      <p>
        <b>code</b>: 
        <span title="Codes: {http://snomed.info/sct 318475005}">Metoprolol tartrate 50mg tablet</span>
      </p>
      <p>
        <b>isBrand</b>: true
      </p>
      <p>
        <b>kind</b>: product
      </p>
      <blockquote>
        <p>
          <b>package</b>
        </p>
        <p>
          <b>container</b>: 
          <span title="Codes: {http://snomed.info/sct 398124009}">drug container</span>
        </p>
      </blockquote>
    </div>
  </text>
  <name value="Metoprolol"/>
  <code>
    <coding>
      <system value="http://snomed.info/sct"/>
      <code value="318475005"/>
      <display value="Metoprolol tartrate 50mg tablet"/>
    </coding>
  </code>
  <isBrand value="true"/>
  <kind value="product"/>
  <package>
    <container>
      <coding>
        <system value="http://snomed.info/sct"/>
        <code value="398124009"/>
        <display value="drug container"/>
      </coding>
    </container>
  </package>
</Medication>